ChuanzhiboKeMybatisKuangjiaKechengJiangyi/README.md
ChuanzhiboKeMybatisKuangjiaKechengJiangyi/__init__.py
ChuanzhiboKeMybatisKuangjiaKechengJiangyi/__main__.py
ChuanzhiboKeMybatisKuangjiaKechengJiangyi/file.pdf
ChuanzhiboKeMybatisKuangjiaKechengJiangyi/index.html
chuanzhibo_ke_mybatis_kuangjia_kecheng_jiangyi-2024.3.2.0.dist-info/METADATA
chuanzhibo_ke_mybatis_kuangjia_kecheng_jiangyi-2024.3.2.0.dist-info/WHEEL
chuanzhibo_ke_mybatis_kuangjia_kecheng_jiangyi-2024.3.2.0.dist-info/entry_points.txt
chuanzhibo_ke_mybatis_kuangjia_kecheng_jiangyi-2024.3.2.0.dist-info/top_level.txt
chuanzhibo_ke_mybatis_kuangjia_kecheng_jiangyi-2024.3.2.0.dist-info/RECORD
